MANIFEST.in
setup.py
hug_store_redis/__init__.py
hug_store_redis/redis_store.py
hug_store_redis.egg-info/PKG-INFO
hug_store_redis.egg-info/SOURCES.txt
hug_store_redis.egg-info/dependency_links.txt
hug_store_redis.egg-info/not-zip-safe
hug_store_redis.egg-info/requires.txt
hug_store_redis.egg-info/top_level.txt