Metadata-Version: 1.1
Name: hug-store-redis
Version: 1.0.0
Summary: Redis Store extension for hug
Home-page: https://github.com/vortec/hug_store_redis
Author: Fabian Kochem
Author-email: fkochem@gmail.com
License: UNKNOWN
Platform: UNKNOWN
Classifier: Development Status :: 3 - Alpha
Classifier: Intended Audience :: Developers
Classifier: License :: OSI Approved :: MIT License
Classifier: Operating System :: OS Independent
Classifier: Programming Language :: Python
Classifier: Programming Language :: Python :: 3
Classifier: Topic :: Database
Classifier: Topic :: Software Development :: Libraries
